racelandshop_frontend/__init__.py
racelandshop_frontend/c.031c4dcb.js
racelandshop_frontend/c.031c4dcb.js.gz
racelandshop_frontend/c.09984bc8.js
racelandshop_frontend/c.09984bc8.js.gz
racelandshop_frontend/c.0fe7c27f.js
racelandshop_frontend/c.0fe7c27f.js.gz
racelandshop_frontend/c.1231cffa.js
racelandshop_frontend/c.1231cffa.js.gz
racelandshop_frontend/c.14c699d0.js
racelandshop_frontend/c.14c699d0.js.gz
racelandshop_frontend/c.14f75282.js
racelandshop_frontend/c.14f75282.js.gz
racelandshop_frontend/c.1558eeb6.js
racelandshop_frontend/c.1558eeb6.js.gz
racelandshop_frontend/c.15cfaaaf.js
racelandshop_frontend/c.15cfaaaf.js.gz
racelandshop_frontend/c.1c18faba.js
racelandshop_frontend/c.1c18faba.js.gz
racelandshop_frontend/c.1d384d2f.js
racelandshop_frontend/c.1d384d2f.js.gz
racelandshop_frontend/c.2b0d6d1d.js
racelandshop_frontend/c.2b0d6d1d.js.gz
racelandshop_frontend/c.3d954156.js
racelandshop_frontend/c.3d954156.js.gz
racelandshop_frontend/c.42f996c8.js
racelandshop_frontend/c.42f996c8.js.gz
racelandshop_frontend/c.48a1c043.js
racelandshop_frontend/c.48a1c043.js.gz
racelandshop_frontend/c.4fb27813.js
racelandshop_frontend/c.4fb27813.js.gz
racelandshop_frontend/c.503303b0.js
racelandshop_frontend/c.503303b0.js.gz
racelandshop_frontend/c.531db01a.js
racelandshop_frontend/c.531db01a.js.gz
racelandshop_frontend/c.711c5a2a.js
racelandshop_frontend/c.711c5a2a.js.gz
racelandshop_frontend/c.79553866.js
racelandshop_frontend/c.79553866.js.gz
racelandshop_frontend/c.81c7aaa8.js
racelandshop_frontend/c.81c7aaa8.js.gz
racelandshop_frontend/c.88a63ccc.js
racelandshop_frontend/c.88a63ccc.js.gz
racelandshop_frontend/c.9f29b77f.js
racelandshop_frontend/c.9f29b77f.js.gz
racelandshop_frontend/c.a1faf29f.js
racelandshop_frontend/c.a1faf29f.js.gz
racelandshop_frontend/c.b4cd1f42.js
racelandshop_frontend/c.b4cd1f42.js.gz
racelandshop_frontend/c.b800b779.js
racelandshop_frontend/c.b800b779.js.gz
racelandshop_frontend/c.bc715c40.js
racelandshop_frontend/c.bc715c40.js.gz
racelandshop_frontend-20210730.3.dist-info/LICENSE
racelandshop_frontend-20210730.3.dist-info/METADATA
racelandshop_frontend-20210730.3.dist-info/WHEEL
racelandshop_frontend-20210730.3.dist-info/top_level.txt
racelandshop_frontend-20210730.3.dist-info/RECORD
