Metadata-Version: 2.1
Name: racelandshop-frontend
Version: 20210730.3
Summary: The RACELANDSHOP frontend
Home-page: https://github.com/racelandshop/frontend
Author: Raceland Automacao
Author-email: geral@automacaoraceland.pt
License: UNKNOWN
Platform: UNKNOWN
License-File: LICENSE
